{
  "id": 3272,
  "slug": "rocket-league",
  "name": "Rocket League",
  "released": "2015-07-07",
  "tba": false,
  "background_image": "https://media.rawg.io/media/games/8cc/8cce7c0e99dcc43d66c8efd42f9d03e3.jpg",
  "rating": 3.93,
  "rating_top": 4,
  "ratings": [
    {
      "id": 4,
      "title": "recommended",
      "count": 1586,
      "percent": 54.94
    },
    {
      "id": 5,
      "title": "exceptional",
      "count": 701,
      "percent": 24.28
    },
    {
      "id": 3,
      "title": "meh",
      "count": 449,
      "percent": 15.55
    },
    {
      "id": 1,
      "title": "skip",
      "count": 151,
      "percent": 5.23
    }
  ],
  "ratings_count": 2863,
  "reviews_text_count": 18,
  "added": 12857,
  "added_by_status": {
    "yet": 194,
    "owned": 9412,
    "beaten": 878,
    "toplay": 111,
    "dropped": 1710,
    "playing": 552
  },
  "metacritic": 86,
  "playtime": 21,
  "suggestions_count": 641,
  "updated": "2026-06-19T09:24:40",
  "user_game": null,
  "reviews_count": 2887,
  "saturated_color": "0f0f0f",
  "dominant_color": "0f0f0f",
  "platforms": [
    {
      "platform": {
        "id": 7,
        "name": "Nintendo Switch",
        "slug": "nintendo-switch",
        "image": null,
        "year_end": null,
        "year_start": null,
        "games_count": 5780,
        "image_background": "https://media.rawg.io/media/games/8a0/8a02f84a5916ede2f923b88d5f8217ba.jpg"
      },
      "released_at": "2015-07-07",
      "requirements_en": null,
      "requirements_ru": null
    },
    {
      "platform": {
        "id": 5,
        "name": "macOS",
        "slug": "macos",
        "image": null,
        "year_end": null,
        "year_start": null,
        "games_count": 108098,
        "image_background": "https://media.rawg.io/media/games/8d6/8d69eb6c32ed6acfd75f82d532144993.jpg"
      },
      "released_at": "2015-07-07",
      "requirements_en": {
        "minimum": "<strong>Minimum:</strong><br><ul class=\"bb_ul\"><li><strong>OS:</strong> MacOS X 10.8.5<br></li><li><strong>Processor:</strong> Intel Core i5 2.4 GHz<br></li><li><strong>Memory:</strong> 8 GB RAM<br></li><li><strong>Graphics:</strong> OpenGL 4.1 - ATI Radeon HD 5670, NVIDIA GeForce GT 640M, Intel HD Graphics 4000 or Iris Pro Graphics<br></li><li><strong>Network:</strong> Broadband Internet connection<br></li><li><strong>Storage:</strong> 7 GB available space</li></ul>",
        "recommended": "<strong>Recommended:</strong><br><ul class=\"bb_ul\"><li><strong>OS:</strong> MacOS X 10.8.5 or Newer<br></li><li><strong>Processor:</strong> Intel Core i7 2.4 GHz+<br></li><li><strong>Memory:</strong> 8 GB RAM<br></li><li><strong>Graphics:</strong> OpenGL 4.1 - ATI Radeon HD 5670, NVIDIA GeForce GT 640M<br></li><li><strong>Network:</strong> Broadband Internet connection<br></li><li><strong>Storage:</strong> 7 GB available space</li></ul>"
      },
      "requirements_ru": null
    },
    {
      "platform": {
        "id": 4,
        "name": "PC",
        "slug": "pc",
        "image": null,
        "year_end": null,
        "year_start": null,
        "games_count": 561169,
        "image_background": "https://media.rawg.io/media/games/4a0/4a0a1316102366260e6f38fd2a9cfdce.jpg"
      },
      "released_at": "2015-07-07",
      "requirements_en": {
        "minimum": "<strong>Minimum:</strong><br><ul class=\"bb_ul\"><li><strong>OS:</strong> Windows 7 or Newer<br></li><li><strong>Processor:</strong> 2.4 GHz Dual core<br></li><li><strong>Memory:</strong> 2 GB RAM<br></li><li><strong>Graphics:</strong> NVIDIA GTX 260 or ATI 4850<br></li><li><strong>DirectX:</strong> Version 9.0c<br></li><li><strong>Network:</strong> Broadband Internet connection<br></li><li><strong>Storage:</strong> 7 GB available space</li></ul>",
        "recommended": "<strong>Recommended:</strong><br><ul class=\"bb_ul\"><li><strong>OS:</strong> Windows 7 or Newer<br></li><li><strong>Processor:</strong> 2.5+ GHz Quad core<br></li><li><strong>Memory:</strong> 4 GB RAM<br></li><li><strong>Graphics:</strong> NVIDIA GTX 660 or better, ATI 7950 or better<br></li><li><strong>DirectX:</strong> Version 9.0c<br></li><li><strong>Network:</strong> Broadband Internet connection<br></li><li><strong>Storage:</strong> 7 GB available space<br></li><li><strong>Additional Notes:</strong> Gamepad or Controller Recommended</li></ul>"
      },
      "requirements_ru": null
    },
    {
      "platform": {
        "id": 6,
        "name": "Linux",
        "slug": "linux",
        "image": null,
        "year_end": null,
        "year_start": null,
        "games_count": 80440,
        "image_background": "https://media.rawg.io/media/games/48c/48cb04ca483be865e3a83119c94e6097.jpg"
      },
      "released_at": "2015-07-07",
      "requirements_en": {
        "minimum": "<strong>Minimum:</strong><br><ul class=\"bb_ul\"><li><strong>Processor:</strong> 2.4+ GHz Quad core<br></li><li><strong>Memory:</strong> 2 GB RAM<br></li><li><strong>Graphics:</strong> NVIDIA GTX 260 or ATI 4850<br></li><li><strong>Network:</strong> Broadband Internet connection<br></li><li><strong>Storage:</strong> 7 GB available space</li></ul>",
        "recommended": "<strong>Recommended:</strong><br><ul class=\"bb_ul\"><li><strong>Processor:</strong> 2.5+ GHz Quad core<br></li><li><strong>Memory:</strong> 4 GB RAM<br></li><li><strong>Graphics:</strong> NVIDIA GTX 660 or better, ATI 7950 or better<br></li><li><strong>Network:</strong> Broadband Internet connection<br></li><li><strong>Storage:</strong> 7 GB available space<br></li><li><strong>Additional Notes:</strong> Gamepad or Controller Recommended</li></ul>"
      },
      "requirements_ru": null
    },
    {
      "platform": {
        "id": 1,
        "name": "Xbox One",
        "slug": "xbox-one",
        "image": null,
        "year_end": null,
        "year_start": null,
        "games_count": 5743,
        "image_background": "https://media.rawg.io/media/games/f46/f466571d536f2e3ea9e815ad17177501.jpg"
      },
      "released_at": "2015-07-07",
      "requirements_en": null,
      "requirements_ru": null
    },
    {
      "platform": {
        "id": 18,
        "name": "PlayStation 4",
        "slug": "playstation4",
        "image": null,
        "year_end": null,
        "year_start": null,
        "games_count": 7037,
        "image_background": "https://media.rawg.io/media/games/20a/20aa03a10cda45239fe22d035c0ebe64.jpg"
      },
      "released_at": "2015-07-07",
      "requirements_en": null,
      "requirements_ru": null
    }
  ],
  "parent_platforms": [
    {
      "platform": {
        "id": 1,
        "name": "PC",
        "slug": "pc"
      }
    },
    {
      "platform": {
        "id": 2,
        "name": "PlayStation",
        "slug": "playstation"
      }
    },
    {
      "platform": {
        "id": 3,
        "name": "Xbox",
        "slug": "xbox"
      }
    },
    {
      "platform": {
        "id": 5,
        "name": "Apple Macintosh",
        "slug": "mac"
      }
    },
    {
      "platform": {
        "id": 6,
        "name": "Linux",
        "slug": "linux"
      }
    },
    {
      "platform": {
        "id": 7,
        "name": "Nintendo",
        "slug": "nintendo"
      }
    }
  ],
  "genres": [
    {
      "id": 15,
      "name": "Sports",
      "slug": "sports",
      "games_count": 22814,
      "image_background": "https://media.rawg.io/media/games/0c1/0c1c9965ba59166ab986a663ab2252dc.jpg"
    },
    {
      "id": 1,
      "name": "Racing",
      "slug": "racing",
      "games_count": 25841,
      "image_background": "https://media.rawg.io/media/games/370/3703c683968a54f09630dcf03366ea35.jpg"
    },
    {
      "id": 51,
      "name": "Indie",
      "slug": "indie",
      "games_count": 86653,
      "image_background": "https://media.rawg.io/media/games/63f/63f0e68688cad279ed38cde931dbfcdb.jpg"
    }
  ],
  "stores": [
    {
      "id": 9319,
      "store": {
        "id": 2,
        "name": "Xbox Store",
        "slug": "xbox-store",
        "domain": "microsoft.com",
        "games_count": 4942,
        "image_background": "https://media.rawg.io/media/games/b45/b45575f34285f2c4479c9a5f719d972e.jpg"
      }
    },
    {
      "id": 10618,
      "store": {
        "id": 1,
        "name": "Steam",
        "slug": "steam",
        "domain": "store.steampowered.com",
        "games_count": 123696,
        "image_background": "https://media.rawg.io/media/games/562/562553814dd54e001a541e4ee83a591c.jpg"
      }
    },
    {
      "id": 3499,
      "store": {
        "id": 3,
        "name": "PlayStation Store",
        "slug": "playstation-store",
        "domain": "store.playstation.com",
        "games_count": 8084,
        "image_background": "https://media.rawg.io/media/games/8d6/8d69eb6c32ed6acfd75f82d532144993.jpg"
      }
    },
    {
      "id": 36994,
      "store": {
        "id": 6,
        "name": "Nintendo Store",
        "slug": "nintendo",
        "domain": "nintendo.com",
        "games_count": 9153,
        "image_background": "https://media.rawg.io/media/games/618/618c2031a07bbff6b4f611f10b6bcdbc.jpg"
      }
    },
    {
      "id": 573307,
      "store": {
        "id": 11,
        "name": "Epic Games",
        "slug": "epic-games",
        "domain": "epicgames.com",
        "games_count": 1454,
        "image_background": "https://media.rawg.io/media/games/021/021c4e21a1824d2526f925eff6324653.jpg"
      }
    }
  ],
  "clip": null,
  "tags": [
    {
      "id": 31,
      "name": "Singleplayer",
      "slug": "singleplayer",
      "language": "eng",
      "games_count": 251054,
      "image_background": "https://media.rawg.io/media/games/4a0/4a0a1316102366260e6f38fd2a9cfdce.jpg"
    },
    {
      "id": 40847,
      "name": "Steam Achievements",
      "slug": "steam-achievements",
      "language": "eng",
      "games_count": 51835,
      "image_background": "https://media.rawg.io/media/games/46d/46d98e6910fbc0706e2948a7cc9b10c5.jpg"
    },
    {
      "id": 7,
      "name": "Multiplayer",
      "slug": "multiplayer",
      "language": "eng",
      "games_count": 42598,
      "image_background": "https://media.rawg.io/media/games/960/960b601d9541cec776c5fa42a00bf6c4.jpg"
    },
    {
      "id": 40836,
      "name": "Full controller support",
      "slug": "full-controller-support",
      "language": "eng",
      "games_count": 24190,
      "image_background": "https://media.rawg.io/media/games/d1a/d1a2e99ade53494c6330a0ed945fe823.jpg"
    },
    {
      "id": 40849,
      "name": "Steam Cloud",
      "slug": "steam-cloud",
      "language": "eng",
      "games_count": 25804,
      "image_background": "https://media.rawg.io/media/games/c6b/c6bfece1daf8d06bc0a60632ac78e5bf.jpg"
    },
    {
      "id": 7808,
      "name": "steam-trading-cards",
      "slug": "steam-trading-cards",
      "language": "eng",
      "games_count": 7568,
      "image_background": "https://media.rawg.io/media/games/46d/46d98e6910fbc0706e2948a7cc9b10c5.jpg"
    },
    {
      "id": 42,
      "name": "Great Soundtrack",
      "slug": "great-soundtrack",
      "language": "eng",
      "games_count": 3450,
      "image_background": "https://media.rawg.io/media/games/b7d/b7d3f1715fa8381a4e780173a197a615.jpg"
    },
    {
      "id": 18,
      "name": "Co-op",
      "slug": "co-op",
      "language": "eng",
      "games_count": 14420,
      "image_background": "https://media.rawg.io/media/games/da1/da1b267764d77221f07a4386b6548e5a.jpg"
    },
    {
      "id": 411,
      "name": "cooperative",
      "slug": "cooperative",
      "language": "eng",
      "games_count": 6603,
      "image_background": "https://media.rawg.io/media/games/4a0/4a0a1316102366260e6f38fd2a9cfdce.jpg"
    },
    {
      "id": 9,
      "name": "Online Co-Op",
      "slug": "online-co-op",
      "language": "eng",
      "games_count": 7705,
      "image_background": "https://media.rawg.io/media/games/4e0/4e0e7b6d6906a131307c94266e5c9a1c.jpg"
    },
    {
      "id": 4,
      "name": "Funny",
      "slug": "funny",
      "language": "eng",
      "games_count": 28871,
      "image_background": "https://media.rawg.io/media/games/25c/25c4776ab5723d5d735d8bf617ca12d9.jpg"
    },
    {
      "id": 198,
      "name": "Split Screen",
      "slug": "split-screen",
      "language": "eng",
      "games_count": 8082,
      "image_background": "https://media.rawg.io/media/games/85c/85c8ae70e7cdf0105f06ef6bdce63b8b.jpg"
    },
    {
      "id": 75,
      "name": "Local Co-Op",
      "slug": "local-co-op",
      "language": "eng",
      "games_count": 6084,
      "image_background": "https://media.rawg.io/media/games/226/2262cea0b385db6cf399f4be831603b0.jpg"
    },
    {
      "id": 72,
      "name": "Local Multiplayer",
      "slug": "local-multiplayer",
      "language": "eng",
      "games_count": 14041,
      "image_background": "https://media.rawg.io/media/games/e74/e74458058b35e01c1ae3feeb39a3f724.jpg"
    },
    {
      "id": 11669,
      "name": "stats",
      "slug": "stats",
      "language": "eng",
      "games_count": 6049,
      "image_background": "https://media.rawg.io/media/games/179/179245a3693049a11a25b900ab18f8f7.jpg"
    },
    {
      "id": 40852,
      "name": "Steam Workshop",
      "slug": "steam-workshop",
      "language": "eng",
      "games_count": 1772,
      "image_background": "https://media.rawg.io/media/games/149/149bbed9d90dc09328ba79bbacfda3c8.jpg"
    },
    {
      "id": 40832,
      "name": "Cross-Platform Multiplayer",
      "slug": "cross-platform-multiplayer",
      "language": "eng",
      "games_count": 3168,
      "image_background": "https://media.rawg.io/media/games/dd5/dd50d4266915d56dd5b63ae1bf72606a.jpg"
    },
    {
      "id": 11,
      "name": "Team-Based",
      "slug": "team-based",
      "language": "eng",
      "games_count": 2078,
      "image_background": "https://media.rawg.io/media/games/476/476178ef18ab0534771d099f51cdc694.jpg"
    },
    {
      "id": 131,
      "name": "Fast-Paced",
      "slug": "fast-paced",
      "language": "eng",
      "games_count": 10824,
      "image_background": "https://media.rawg.io/media/games/e04/e04963f3ac4c4fa83a1dc0b9231e50db.jpg"
    },
    {
      "id": 170,
      "name": "Competitive",
      "slug": "competitive",
      "language": "eng",
      "games_count": 1314,
      "image_background": "https://media.rawg.io/media/games/abd/abdb7e589f0a8ccd36c0582673120b1e.jpg"
    },
    {
      "id": 182,
      "name": "4 Player Local",
      "slug": "4-player-local",
      "language": "eng",
      "games_count": 1631,
      "image_background": "https://media.rawg.io/media/games/843/843499f98a871098e3e365a80b5c8768.jpg"
    },
    {
      "id": 87822,
      "name": "4 giocatori divano",
      "slug": "4-giocatori-divano",
      "language": "eng",
      "games_count": 32,
      "image_background": "https://media.rawg.io/media/games/82e/82eeea65ebb047cc7f366faf2fb062b6.jpg"
    },
    {
      "id": 191,
      "name": "Football",
      "slug": "football",
      "language": "eng",
      "games_count": 2042,
      "image_background": "https://media.rawg.io/media/games/9ca/9ca31615beee447f3ae1dc9b3b736dce.jpg"
    },
    {
      "id": 190,
      "name": "Soccer",
      "slug": "soccer",
      "language": "eng",
      "games_count": 1834,
      "image_background": "https://media.rawg.io/media/screenshots/3ea/3ea3f535b2a779ca5cd2e466a2f8abba.jpg"
    },
    {
      "id": 87821,
      "name": "lan party",
      "slug": "lan-party-2",
      "language": "eng",
      "games_count": 3,
      "image_background": "https://media.rawg.io/media/games/8cc/8cce7c0e99dcc43d66c8efd42f9d03e3.jpg"
    }
  ],
  "esrb_rating": {
    "id": 1,
    "name": "Everyone",
    "slug": "everyone"
  },
  "short_screenshots": [
    {
      "id": -1,
      "image": "https://media.rawg.io/media/games/8cc/8cce7c0e99dcc43d66c8efd42f9d03e3.jpg"
    },
    {
      "id": 29880,
      "image": "https://media.rawg.io/media/screenshots/6a0/6a0745d9dcd0f7a368d372260baf91aa.jpg"
    },
    {
      "id": 29881,
      "image": "https://media.rawg.io/media/screenshots/5ea/5ea8ab6a35f189489b2ec8713d4f1619.jpg"
    },
    {
      "id": 29882,
      "image": "https://media.rawg.io/media/screenshots/508/5083fd170bf10606afd12afc7d17db04.jpg"
    },
    {
      "id": 29883,
      "image": "https://media.rawg.io/media/screenshots/02d/02d36e8e01a9f1063c6431ce09324e24.jpg"
    },
    {
      "id": 29884,
      "image": "https://media.rawg.io/media/screenshots/036/036ddade8156ac52ecf8de593123d12c.jpg"
    },
    {
      "id": 29885,
      "image": "https://media.rawg.io/media/screenshots/861/8615727f6e52f1632ae38d71e9e4c800.jpg"
    }
  ]
}