{
  "id": 654,
  "slug": "stardew-valley",
  "name": "Stardew Valley",
  "released": "2016-02-25",
  "tba": false,
  "background_image": "https://media.rawg.io/media/games/713/713269608dc8f2f40f5a670a14b2de94.jpg",
  "rating": 4.39,
  "rating_top": 5,
  "ratings": [
    {
      "id": 5,
      "title": "exceptional",
      "count": 1414,
      "percent": 56.47
    },
    {
      "id": 4,
      "title": "recommended",
      "count": 785,
      "percent": 31.35
    },
    {
      "id": 3,
      "title": "meh",
      "count": 238,
      "percent": 9.5
    },
    {
      "id": 1,
      "title": "skip",
      "count": 67,
      "percent": 2.68
    }
  ],
  "ratings_count": 2469,
  "reviews_text_count": 24,
  "added": 11056,
  "added_by_status": {
    "yet": 487,
    "owned": 7121,
    "beaten": 1103,
    "toplay": 376,
    "dropped": 1223,
    "playing": 746
  },
  "metacritic": 89,
  "playtime": 13,
  "suggestions_count": 301,
  "updated": "2026-06-19T09:43:57",
  "user_game": null,
  "reviews_count": 2504,
  "saturated_color": "0f0f0f",
  "dominant_color": "0f0f0f",
  "platforms": [
    {
      "platform": {
        "id": 7,
        "name": "Nintendo Switch",
        "slug": "nintendo-switch",
        "image": null,
        "year_end": null,
        "year_start": null,
        "games_count": 5780,
        "image_background": "https://media.rawg.io/media/games/8a0/8a02f84a5916ede2f923b88d5f8217ba.jpg"
      },
      "released_at": "2016-02-25",
      "requirements_en": null,
      "requirements_ru": null
    },
    {
      "platform": {
        "id": 1,
        "name": "Xbox One",
        "slug": "xbox-one",
        "image": null,
        "year_end": null,
        "year_start": null,
        "games_count": 5743,
        "image_background": "https://media.rawg.io/media/games/f46/f466571d536f2e3ea9e815ad17177501.jpg"
      },
      "released_at": "2016-02-25",
      "requirements_en": null,
      "requirements_ru": null
    },
    {
      "platform": {
        "id": 4,
        "name": "PC",
        "slug": "pc",
        "image": null,
        "year_end": null,
        "year_start": null,
        "games_count": 561169,
        "image_background": "https://media.rawg.io/media/games/4a0/4a0a1316102366260e6f38fd2a9cfdce.jpg"
      },
      "released_at": "2016-02-25",
      "requirements_en": null,
      "requirements_ru": null
    },
    {
      "platform": {
        "id": 3,
        "name": "iOS",
        "slug": "ios",
        "image": null,
        "year_end": null,
        "year_start": null,
        "games_count": 77452,
        "image_background": "https://media.rawg.io/media/games/283/283e7e600366b0da7021883d27159b27.jpg"
      },
      "released_at": "2016-02-25",
      "requirements_en": {
        "minimum": "iPhone 5, iPad Fourth Gen, iPad Fourth Gen 4G, iPhone 5c, iPhone 5s, iPad Air, iPad Air Cellular, iPad Mini Retina, iPad Mini Retina Cellular, iPhone 6, iPhone 6 Plus, iPad Air 2, iPad Air 2 Cellular, iPad Mini 3, iPad Mini 3 Cellular, iPod Touch Sixth Gen, iPhone 6s, iPhone 6s Plus, iPad Mini 4, iPad Mini 4 Cellular, iPad Pro, iPad Pro Cellular, iPad Pro 9.7, iPad Pro 9.7 Cellular, iPhone SE, iPhone 7, iPhone 7 Plus, iPad 6 1 1, iPad 6 1 2, iPad 7 1, iPad 7 2, iPad 7 3, iPad 7 4, iPhone 8, iPhone 8 Plus, iPhone X, iPad 7 5, iPad 7 6, iPhone X S, iPhone X S Max, iPhone X R, iPad 8 1 2, iPad 8 3 4, iPad 8 5 6, iPad 8 7 8,  Watch 4, iPad Mini 5, iPad Mini 5 Cellular, iPad Air 3, iPad Air 3 Cellular, iPod Touch Seventh Gen"
      },
      "requirements_ru": null
    },
    {
      "platform": {
        "id": 5,
        "name": "macOS",
        "slug": "macos",
        "image": null,
        "year_end": null,
        "year_start": null,
        "games_count": 108098,
        "image_background": "https://media.rawg.io/media/games/8d6/8d69eb6c32ed6acfd75f82d532144993.jpg"
      },
      "released_at": "2016-02-25",
      "requirements_en": null,
      "requirements_ru": null
    },
    {
      "platform": {
        "id": 6,
        "name": "Linux",
        "slug": "linux",
        "image": null,
        "year_end": null,
        "year_start": null,
        "games_count": 80440,
        "image_background": "https://media.rawg.io/media/games/48c/48cb04ca483be865e3a83119c94e6097.jpg"
      },
      "released_at": "2016-02-25",
      "requirements_en": null,
      "requirements_ru": null
    },
    {
      "platform": {
        "id": 18,
        "name": "PlayStation 4",
        "slug": "playstation4",
        "image": null,
        "year_end": null,
        "year_start": null,
        "games_count": 7037,
        "image_background": "https://media.rawg.io/media/games/20a/20aa03a10cda45239fe22d035c0ebe64.jpg"
      },
      "released_at": "2016-02-25",
      "requirements_en": null,
      "requirements_ru": null
    },
    {
      "platform": {
        "id": 19,
        "name": "PS Vita",
        "slug": "ps-vita",
        "image": null,
        "year_end": null,
        "year_start": null,
        "games_count": 1461,
        "image_background": "https://media.rawg.io/media/games/f99/f9979698c43fd84c3ab69280576dd3af.jpg"
      },
      "released_at": "2016-02-25",
      "requirements_en": null,
      "requirements_ru": null
    },
    {
      "platform": {
        "id": 21,
        "name": "Android",
        "slug": "android",
        "image": null,
        "year_end": null,
        "year_start": null,
        "games_count": 52534,
        "image_background": "https://media.rawg.io/media/games/e04/e04963f3ac4c4fa83a1dc0b9231e50db.jpg"
      },
      "released_at": "2016-02-25",
      "requirements_en": {
        "minimum": "4.4 and up"
      },
      "requirements_ru": null
    }
  ],
  "parent_platforms": [
    {
      "platform": {
        "id": 1,
        "name": "PC",
        "slug": "pc"
      }
    },
    {
      "platform": {
        "id": 2,
        "name": "PlayStation",
        "slug": "playstation"
      }
    },
    {
      "platform": {
        "id": 3,
        "name": "Xbox",
        "slug": "xbox"
      }
    },
    {
      "platform": {
        "id": 4,
        "name": "iOS",
        "slug": "ios"
      }
    },
    {
      "platform": {
        "id": 8,
        "name": "Android",
        "slug": "android"
      }
    },
    {
      "platform": {
        "id": 5,
        "name": "Apple Macintosh",
        "slug": "mac"
      }
    },
    {
      "platform": {
        "id": 6,
        "name": "Linux",
        "slug": "linux"
      }
    },
    {
      "platform": {
        "id": 7,
        "name": "Nintendo",
        "slug": "nintendo"
      }
    }
  ],
  "genres": [
    {
      "id": 5,
      "name": "RPG",
      "slug": "role-playing-games-rpg",
      "games_count": 62046,
      "image_background": "https://media.rawg.io/media/games/a6c/a6ccd34125c594abf1a9c9821b9a715d.jpg"
    },
    {
      "id": 14,
      "name": "Simulation",
      "slug": "simulation",
      "games_count": 77025,
      "image_background": "https://media.rawg.io/media/games/e40/e40cc9d1957b0a0ed7e389834457b524.jpg"
    },
    {
      "id": 51,
      "name": "Indie",
      "slug": "indie",
      "games_count": 86653,
      "image_background": "https://media.rawg.io/media/games/63f/63f0e68688cad279ed38cde931dbfcdb.jpg"
    }
  ],
  "stores": [
    {
      "id": 661,
      "store": {
        "id": 3,
        "name": "PlayStation Store",
        "slug": "playstation-store",
        "domain": "store.playstation.com",
        "games_count": 8084,
        "image_background": "https://media.rawg.io/media/games/8d6/8d69eb6c32ed6acfd75f82d532144993.jpg"
      }
    },
    {
      "id": 256975,
      "store": {
        "id": 4,
        "name": "App Store",
        "slug": "apple-appstore",
        "domain": "apps.apple.com",
        "games_count": 75593,
        "image_background": "https://media.rawg.io/media/games/095/0953bf01cd4e4dd204aba85489ac9868.jpg"
      }
    },
    {
      "id": 9177,
      "store": {
        "id": 2,
        "name": "Xbox Store",
        "slug": "xbox-store",
        "domain": "microsoft.com",
        "games_count": 4942,
        "image_background": "https://media.rawg.io/media/games/b45/b45575f34285f2c4479c9a5f719d972e.jpg"
      }
    },
    {
      "id": 10356,
      "store": {
        "id": 1,
        "name": "Steam",
        "slug": "steam",
        "domain": "store.steampowered.com",
        "games_count": 123696,
        "image_background": "https://media.rawg.io/media/games/562/562553814dd54e001a541e4ee83a591c.jpg"
      }
    },
    {
      "id": 26627,
      "store": {
        "id": 5,
        "name": "GOG",
        "slug": "gog",
        "domain": "gog.com",
        "games_count": 7397,
        "image_background": "https://media.rawg.io/media/games/ee3/ee3e10193aafc3230ba1cae426967d10.jpg"
      }
    },
    {
      "id": 33129,
      "store": {
        "id": 6,
        "name": "Nintendo Store",
        "slug": "nintendo",
        "domain": "nintendo.com",
        "games_count": 9153,
        "image_background": "https://media.rawg.io/media/games/618/618c2031a07bbff6b4f611f10b6bcdbc.jpg"
      }
    },
    {
      "id": 307327,
      "store": {
        "id": 8,
        "name": "Google Play",
        "slug": "google-play",
        "domain": "play.google.com",
        "games_count": 17128,
        "image_background": "https://media.rawg.io/media/games/35b/35b47c4d85cd6e08f3e2ca43ea5ce7bb.jpg"
      }
    }
  ],
  "clip": null,
  "tags": [
    {
      "id": 31,
      "name": "Singleplayer",
      "slug": "singleplayer",
      "language": "eng",
      "games_count": 251054,
      "image_background": "https://media.rawg.io/media/games/4a0/4a0a1316102366260e6f38fd2a9cfdce.jpg"
    },
    {
      "id": 40847,
      "name": "Steam Achievements",
      "slug": "steam-achievements",
      "language": "eng",
      "games_count": 51835,
      "image_background": "https://media.rawg.io/media/games/46d/46d98e6910fbc0706e2948a7cc9b10c5.jpg"
    },
    {
      "id": 7,
      "name": "Multiplayer",
      "slug": "multiplayer",
      "language": "eng",
      "games_count": 42598,
      "image_background": "https://media.rawg.io/media/games/960/960b601d9541cec776c5fa42a00bf6c4.jpg"
    },
    {
      "id": 40849,
      "name": "Steam Cloud",
      "slug": "steam-cloud",
      "language": "eng",
      "games_count": 25804,
      "image_background": "https://media.rawg.io/media/games/c6b/c6bfece1daf8d06bc0a60632ac78e5bf.jpg"
    },
    {
      "id": 13,
      "name": "Atmospheric",
      "slug": "atmospheric",
      "language": "eng",
      "games_count": 39763,
      "image_background": "https://media.rawg.io/media/games/942/9424d6bb763dc38d9378b488603c87fa.jpg"
    },
    {
      "id": 7808,
      "name": "steam-trading-cards",
      "slug": "steam-trading-cards",
      "language": "eng",
      "games_count": 7568,
      "image_background": "https://media.rawg.io/media/games/46d/46d98e6910fbc0706e2948a7cc9b10c5.jpg"
    },
    {
      "id": 42,
      "name": "Great Soundtrack",
      "slug": "great-soundtrack",
      "language": "eng",
      "games_count": 3450,
      "image_background": "https://media.rawg.io/media/games/b7d/b7d3f1715fa8381a4e780173a197a615.jpg"
    },
    {
      "id": 24,
      "name": "RPG",
      "slug": "rpg",
      "language": "eng",
      "games_count": 26681,
      "image_background": "https://media.rawg.io/media/games/d82/d82990b9c67ba0d2d09d4e6fa88885a7.jpg"
    },
    {
      "id": 18,
      "name": "Co-op",
      "slug": "co-op",
      "language": "eng",
      "games_count": 14420,
      "image_background": "https://media.rawg.io/media/games/da1/da1b267764d77221f07a4386b6548e5a.jpg"
    },
    {
      "id": 36,
      "name": "Open World",
      "slug": "open-world",
      "language": "eng",
      "games_count": 9281,
      "image_background": "https://media.rawg.io/media/games/49c/49c3dfa4ce2f6f140cc4825868e858cb.jpg"
    },
    {
      "id": 45,
      "name": "2D",
      "slug": "2d",
      "language": "eng",
      "games_count": 207863,
      "image_background": "https://media.rawg.io/media/games/ffe/ffed87105b14f5beff72ff44a7793fd5.jpg"
    },
    {
      "id": 40845,
      "name": "Partial Controller Support",
      "slug": "partial-controller-support",
      "language": "eng",
      "games_count": 14005,
      "image_background": "https://media.rawg.io/media/games/960/960b601d9541cec776c5fa42a00bf6c4.jpg"
    },
    {
      "id": 37,
      "name": "Sandbox",
      "slug": "sandbox",
      "language": "eng",
      "games_count": 8523,
      "image_background": "https://media.rawg.io/media/games/095/0953bf01cd4e4dd204aba85489ac9868.jpg"
    },
    {
      "id": 122,
      "name": "Pixel Graphics",
      "slug": "pixel-graphics",
      "language": "eng",
      "games_count": 99378,
      "image_background": "https://media.rawg.io/media/screenshots/2fc/2fc6994425146f9dba3133400b414e29.jpg"
    },
    {
      "id": 74,
      "name": "Retro",
      "slug": "retro",
      "language": "eng",
      "games_count": 44680,
      "image_background": "https://media.rawg.io/media/games/fd7/fd794a9f0ffe816038d981b3acc3eec9.jpg"
    },
    {
      "id": 468,
      "name": "role-playing",
      "slug": "role-playing",
      "language": "eng",
      "games_count": 1657,
      "image_background": "https://media.rawg.io/media/games/840/8408ad3811289a6a5830cae60fb0b62a.jpg"
    },
    {
      "id": 88,
      "name": "Cute",
      "slug": "cute",
      "language": "eng",
      "games_count": 39831,
      "image_background": "https://media.rawg.io/media/games/d03/d030347839f74454afcd1008248b08ae.jpg"
    },
    {
      "id": 125,
      "name": "Crafting",
      "slug": "crafting",
      "language": "eng",
      "games_count": 5538,
      "image_background": "https://media.rawg.io/media/games/87a/87a29bcc56b6b6082ead1dd5e2510aaa.jpg"
    },
    {
      "id": 39,
      "name": "Building",
      "slug": "building",
      "language": "eng",
      "games_count": 7544,
      "image_background": "https://media.rawg.io/media/games/d03/d030347839f74454afcd1008248b08ae.jpg"
    },
    {
      "id": 337,
      "name": "overlay",
      "slug": "overlay",
      "language": "eng",
      "games_count": 217,
      "image_background": "https://media.rawg.io/media/games/7ba/7baf4663962bad7197e2470d59a6e322.jpg"
    },
    {
      "id": 138,
      "name": "Relaxing",
      "slug": "relaxing",
      "language": "eng",
      "games_count": 21559,
      "image_background": "https://media.rawg.io/media/screenshots/ed0/ed006da5dfcf9d97d34a7f065769d18b.jpeg"
    },
    {
      "id": 160,
      "name": "Dating Sim",
      "slug": "dating-sim",
      "language": "eng",
      "games_count": 6831,
      "image_background": "https://media.rawg.io/media/games/81e/81e5cf3f433473af3a04888e3baceeba.jpg"
    },
    {
      "id": 46112,
      "name": "Shared/Split Screen Co-op",
      "slug": "sharedsplit-screen-co-op",
      "language": "eng",
      "games_count": 2623,
      "image_background": "https://media.rawg.io/media/games/e79/e7901bf8d36cf8ebaf4886d8cd28c7e4.jpg"
    },
    {
      "id": 338,
      "name": "cloud saves",
      "slug": "cloud-saves",
      "language": "eng",
      "games_count": 37,
      "image_background": "https://media.rawg.io/media/screenshots/599/599aa44b6c50fba1e46a829ac67d9b33.jpg"
    },
    {
      "id": 155,
      "name": "Fishing",
      "slug": "fishing",
      "language": "eng",
      "games_count": 2196,
      "image_background": "https://media.rawg.io/media/games/196/196381a3afc69bd73d4374fdbf5ef774.jpg"
    },
    {
      "id": 159,
      "name": "Agriculture",
      "slug": "agriculture",
      "language": "eng",
      "games_count": 869,
      "image_background": "https://media.rawg.io/media/screenshots/c9f/c9f6a267a08609d634d62473173e8f0d.jpg"
    },
    {
      "id": 409,
      "name": "co-op multiplayer",
      "slug": "co-op-multiplayer",
      "language": "eng",
      "games_count": 8,
      "image_background": "https://media.rawg.io/media/games/d22/d22ea1bfb636fbf1a9c235cc304312a8.jpg"
    }
  ],
  "esrb_rating": {
    "id": 2,
    "name": "Everyone 10+",
    "slug": "everyone-10-plus"
  },
  "short_screenshots": [
    {
      "id": -1,
      "image": "https://media.rawg.io/media/games/713/713269608dc8f2f40f5a670a14b2de94.jpg"
    },
    {
      "id": 5702,
      "image": "https://media.rawg.io/media/screenshots/b72/b722b1746256f64ce5e15558d1ac7613.jpg"
    },
    {
      "id": 5704,
      "image": "https://media.rawg.io/media/screenshots/733/7330aea66ef9de06bb201e1d3f10ff70.jpg"
    },
    {
      "id": 5706,
      "image": "https://media.rawg.io/media/screenshots/0a6/0a6dfc3ef9ac018b737427405e686e23.jpg"
    },
    {
      "id": 5707,
      "image": "https://media.rawg.io/media/screenshots/366/3668bbdd41a682c76370fc81691150bc.jpg"
    },
    {
      "id": 59238,
      "image": "https://media.rawg.io/media/screenshots/e25/e25137cf398c743153d64993160487f1.jpg"
    },
    {
      "id": 59242,
      "image": "https://media.rawg.io/media/screenshots/b64/b6419e71b81f36ab7bc62a6614cb5b85.jpg"
    }
  ]
}